dobyemail/__init__.py
dobyemail/check_ports.py
dobyemail/config.py
dobyemail/email_ports.json
dobyemail/get_email_ports.py
dobyemail/is_valid_email.py
dobyemail/parse_date.py
dobyemail/reader.py
dobyemail/sender.py
dobyemail/service.py
dobyemail/transfer.py
dobyemail-0.1.6.dist-info/LICENSE
dobyemail-0.1.6.dist-info/METADATA
dobyemail-0.1.6.dist-info/WHEEL
dobyemail-0.1.6.dist-info/top_level.txt
dobyemail-0.1.6.dist-info/RECORD
