Metadata-Version: 2.1
Name: dobyemail
Version: 0.1.6
Summary: Do By Email is a comprehensive Python package for handling various email operations.
Home-page: https://python.dobyemail.com
Author: Tom Sapletta
Author-email: info@softreck.dev
Classifier: Development Status :: 3 - Alpha
Classifier: Intended Audience :: Developers
Classifier: License :: OSI Approved :: Apache Software License
Classifier: Operating System :: OS Independent
Classifier: Programming Language :: Python :: 3
Classifier: Programming Language :: Python :: 3.6
Classifier: Programming Language :: Python :: 3.7
Classifier: Programming Language :: Python :: 3.8
Classifier: Programming Language :: Python :: 3.9
Requires-Python: >=3.6
License-File: LICENSE
Requires-Dist: python-dateutil >=2.8.2
